bwreceive/__init__.py
bwreceive/__main__.py
bwreceive-0.1.1.dist-info/METADATA
bwreceive-0.1.1.dist-info/WHEEL
bwreceive-0.1.1.dist-info/entry_points.txt
bwreceive-0.1.1.dist-info/licenses/LICENSE
bwreceive-0.1.1.dist-info/RECORD
