Metadata-Version: 2.4
Name: bwreceive
Version: 0.1.1
Summary: bwreceive is a wrapper around bw-cli to display bitwarden send password
License-File: LICENSE
Requires-Python: >=3.12
Requires-Dist: hatch
Requires-Dist: pygobject
Requires-Dist: zenipy
